[{"t":"HOMCOM Covor de țară, versatil, din poliester, ușor de întreținut, antiderapant, colorat | Aosom Romania","i":"https://img.aosomcdn.com/100/product/2025/08/06/xiEb521988144c42b.jpg","l":"/go/p/H013LutNZAJB/2ace29e87/573b44539","b":"HOMCOM","m":"aosom.ro","c":"Mobila si decoratiuni > Mobila living > Covoare","p":349.99},{"t":"HOMCOM Covor Modern Antiderapant cu Linii Geometrice din Poliester, Multicolor | Aosom Romania","i":"https://img.aosomcdn.com/100/product/2025/08/14/ufN9e0198a89076df.jpg","l":"/go/p/VXCoCPwIFTcJ/2ace29e87/573b44539","b":"HOMCOM","m":"aosom.ro","c":"Mobila si decoratiuni > Mobila living > Covoare","p":339.99},{"t":"Covor tip casmir Heinner HR-RUG200CSH-YEN, 200 x 300 cm, poliester 100%, spate antiderapant","i":"https://static2.evomag.ro/img?extend=white&file=products%2F4211%2F4211445%2Foverlay_092a0a524f8e1f548923b7b02615aac3.jpg&type=auto&width=500&sign=g008Vt9wWaiEIu7NNpx7i_ucUwKCHC1lr2yl9VA_k8U","l":"/go/p/97cbba260/2ace29e87/d4f678b43","b":"Heinner","m":"evomag.ro","c":"Covoare","p":518.99},{"t":"Covor tip casmir Heinner HR-RUG200CSH-RTZ, 200 x 300 cm, poliester 100%, spate antiderapant","i":"https://static2.evomag.ro/img?extend=white&file=products%2F4211%2F4211446%2Foverlay_43d491e0923dfd56f48931052e6bbf58.jpg&type=auto&width=500&sign=r3zvtFGzQ5lTwMXyPCQssP-w9XNwCz4DMJyKGAweOw4","l":"/go/p/a6a4adebc/2ace29e87/d4f678b43","b":"Heinner","m":"evomag.ro","c":"Covoare","p":518.99},{"t":"Covor tip casmir Heinner HR-RUG200CSH-MLA, 200 x 300 cm, poliester 100%, spate antiderapant","i":"https://static2.evomag.ro/img?extend=white&file=products%2F4211%2F4211447%2Foverlay_23d4c239e0f5e5aec3daaf579c66bfc5.jpg&type=auto&width=500&sign=-d6Jm9ShTsH0KUuZUvFj9PfOEDb9UjLKOBpOuhD62E8","l":"/go/p/66c65390b/2ace29e87/d4f678b43","b":"Heinner","m":"evomag.ro","c":"Covoare","p":518.99},{"t":"Covor Heinner Home Yen, tip casmir, 160 x 230 cm, poliester 100%, spate antiderapant","i":"https://static2.evomag.ro/img?extend=white&file=products%2F4210%2F4210560%2F67dac52c79214.jpg&type=auto&width=500&sign=NEblEabVqjaqel7oPaLvE8-frOu4a7rRYlNWLPPd-w0","l":"/go/p/50580e4d5/2ace29e87/d4f678b43","b":"Heinner","m":"evomag.ro","c":"Covoare","p":317.99},{"t":"Covor Heinner Home Ritz, tip casmir, 160 x 230 cm, poliester 100%, spate antiderapant","i":"https://static2.evomag.ro/img?extend=white&file=products%2F4210%2F4210561%2F67dac531a5788.jpg&type=auto&width=500&sign=VURv4X7KQY-cEK8eFgt0vAhMbMznBErmvPZ-_LwU7a8","l":"/go/p/4229cc8f9/2ace29e87/d4f678b43","b":"Heinner","m":"evomag.ro","c":"Covoare","p":317.99},{"t":"Covor Heinner Home Mila, tip casmir, 160 x 230 cm, poliester 100%, spate antiderapant","i":"https://static2.evomag.ro/img?extend=white&file=products%2F4211%2F4211462%2Foverlay_d69c43cec22caca6db6e4fd7fc5dd976.jpg&type=auto&width=500&sign=NHcJ7Ojj20xsOxuvL5Y2U_sCgo5La7W7JVBUxCOi4bk","l":"/go/p/4ed5c4652/2ace29e87/d4f678b43","b":"Heinner","m":"evomag.ro","c":"Covoare","p":317.99},{"t":"Covor cu print digital 3D Artic Heinner Home, 200x300 cm, poliester 100%, spate antiderapant","i":"https://static2.evomag.ro/img?extend=white&file=products%2F4210%2F4210563%2F67dac52213752.jpg&type=auto&width=500&sign=80S-PclsZi9sub-XCj9pfxNjGlTMx7H2EEQ7hO9oYp4","l":"/go/p/e5e5187f4/2ace29e87/d4f678b43","b":"Heinner","m":"evomag.ro","c":"Covoare","p":306.99},{"t":"Covor cu print digital 3D Heinner HR-3DRUG200-VOX, 200x300 cm, poliester 100%, spate antiderapant (Multicolor)","i":"https://static2.evomag.ro/img?extend=white&file=products%2F4211%2F4211420%2Foverlay_314b16cf77dd8746e92ccd6786fb874a.jpg&type=auto&width=500&sign=oPGz5GezUUyfKLaXlFG4tBxqx6TvfxR2CXFWptH6qac","l":"/go/p/958787955/2ace29e87/d4f678b43","b":"Heinner","m":"evomag.ro","c":"Covoare","p":306.99},{"t":"Covor cu print digital 3D Heinner HR-3DRUG200-LEA, 200x300 cm, poliester 100%, spate antiderapant (Multicolor)","i":"https://static2.evomag.ro/img?extend=white&file=products%2F4211%2F4211421%2Foverlay_0a489e10b8c252ea356cd9dbeee17a70.jpg&type=auto&width=500&sign=5V5b3Rg-m3O_WCWkqR0mpXbxf-rfsydsdnVYdNnJTjY","l":"/go/p/7f52970a7/2ace29e87/d4f678b43","b":"Heinner","m":"evomag.ro","c":"Covoare","p":306.99},{"t":"Covor cu print digital 3D Heinner HR-3DRUG200-INK, 200x300 cm, poliester 100%, spate antiderapant (Multicolor)","i":"https://static2.evomag.ro/img?extend=white&file=products%2F4211%2F4211422%2Foverlay_216000d023f0554a3c9a23f7b2404253.jpg&type=auto&width=500&sign=nShPhfHL6w23uRjJedHnkT4h_TO6gXNRTRQKssnws1Q","l":"/go/p/3790e833c/2ace29e87/d4f678b43","b":"Heinner","m":"evomag.ro","c":"Covoare","p":306.99},{"t":"Covor cu print digital 3D Heinner HR-3DRUG200-DRM, 200x300 cm, poliester 100%, spate antiderapant (Multicolor)","i":"https://static2.evomag.ro/img?extend=white&file=products%2F4211%2F4211423%2Foverlay_805fdea5bb17fd9dd803428515e0496e.jpg&type=auto&width=500&sign=cZ6eWyTcrfVppk9Svmob0a9lna_-xFGxxRmLVwNJiOQ","l":"/go/p/118c51750/2ace29e87/d4f678b43","b":"Heinner","m":"evomag.ro","c":"Covoare","p":306.99},{"t":"Covor cu print digital 3D Heinner HR-3DRUG200-CLT, 200x300 cm, poliester 100%, spate antiderapant (Multicolor)","i":"https://static2.evomag.ro/img?extend=white&file=products%2F4211%2F4211424%2Foverlay_add082e82d0c6c1541007c435e9554aa.jpg&type=auto&width=500&sign=VVP9a45A4gIO6bevK487GuQ-5yCCOqe9pSk-eyN7Dis","l":"/go/p/f158476be/2ace29e87/d4f678b43","b":"Heinner","m":"evomag.ro","c":"Covoare","p":306.99}]