[{"t":"Laptop gaming Asus TUF F16 FX608JPR, 16\", I5-14450HX, 16GB DDR5, 1TB SSD, NVIDIA GeForce RTX 5070, Free DOS, Negru/Gri","i":"https://www.flanco.ro/media/catalog/product/6/9/69406969b7f26e0304e8.22833859.jpeg","l":"/go/p/bhPAWHHDablM/2ace29e87/ea7857c9c","b":"Asus","m":"flanco.ro","c":"Gaming Laptop","p":7749.99},{"t":"Laptop gaming ASUS TUF F16 FX608JPR-RV108,16\" Intel Core i5-14450HX, 16GB, 512GB SSD, 10 nuclee, NVIDIA GeForce RTX 5070, Negru/Gri","i":"https://www.flanco.ro/media/catalog/product/6/9/69407069b7f4a53b37c5.95862803.jpeg","l":"/go/p/N8rYa_wxDYEy/2ace29e87/ea7857c9c","b":"Asus","m":"flanco.ro","c":"Gaming Laptop","p":7527.99},{"t":"Laptop Gaming ASUS TUF Gaming F16 FX608JHR-RV109, 16\", Intel Core i5-14450HX, NVIDIA GeForce RTX 5050 8GB GDDR7, 16GB DDR5, Jaeger Gray","i":"https://www.flanco.ro/media/catalog/product/6/9/69392569b7ba0128b234.22546897.jpeg","l":"/go/p/RDv2gVJpxzxK/2ace29e87/ea7857c9c","b":"Asus","m":"flanco.ro","c":"Gaming Laptop","p":6397.99},{"t":"Laptop Gaming ASUS ROG Zephyrus G16 OLED GU605CX (Procesor Intel® Core™ Ultra 9 285H (24M Cache, up to 5.40 GHz), 16inch 2.5K 240Hz G-Sync, 64GB LPDDR5X, 1TB SSD, NVIDIA GeForce RTX 5090 @24GB, Gri)","i":"https://static2.evomag.ro/img?extend=white&file=products%2F4219%2F4219186%2Flaptop-gaming-asus-rog-zephyru-6814ac70742ba.jpg&type=auto&width=500&sign=48Z1jwIQyHO3ngROm72hPHNa7_ur5ZA1c5a5I58MDPk","l":"/go/p/6565190ea/2ace29e87/d4f678b43","b":"ASUS","m":"evomag.ro","c":"Laptopuri / Notebook","p":21999.99},{"t":"Laptop Gaming ASUS ROG Strix G16 G615LR (Procesor Intel® Core™ Ultra 7 255HX (30M Cache, up to 5.20 GHz), 16inch 2.5K 240Hz, 32GB, 1TB SSD, NVIDIA GeForce RTX 5070 Ti @12GB, Negru/Gri)","i":"https://static2.evomag.ro/img?extend=white&file=products%2F4228%2F4228274%2Flaptop-gaming-asus-rog-strix-g-683d9b161e34b.jpg&type=auto&width=500&sign=HBgH63AqaXPKk-62LQqHusCOWBoZqkTUQIRZco2ydAY","l":"/go/p/s31u_EoxHCgX/2ace29e87/d4f678b43","b":"ASUS","m":"evomag.ro","c":"Laptopuri / Notebook","p":14199.99},{"t":"Laptop Gaming ASUS ROG Strix G18 G815LM (Procesor Intel® Core™ Ultra 9 275HX (36M Cache, up to 5.40 GHz), 18inch 2.5K 240Hz, 32GB DDR5, 1TB SSD, NVIDIA GeForce RTX 5060 @8GB, Negru/Gri)","i":"https://static2.evomag.ro/img?extend=white&file=products%2F4243%2F4243594%2Flaptop-gaming-asus-rog-strix-g-6811dbf665f8d.jpg&type=auto&width=500&sign=M0FY7j53Jegrl0UCkT8ZhRDK_J5g33XtAVHt6Ab-pT4","l":"/go/p/zbl1RQFkxl6z/2ace29e87/d4f678b43","b":"ASUS","m":"evomag.ro","c":"Laptopuri / Notebook","p":11299.99},{"t":"Laptop Gaming ASUS ROG Strix G18 G814FP (Procesor AMD Ryzen™ 9 9955HX (64M Cache, up to 5.40 GHz), 18inch FHD+ 144Hz, 32GB, 1TB SSD, NVIDIA GeForce RTX 5070 @8GB, Negru/Gri)","i":"https://static2.evomag.ro/img?extend=white&file=products%2F4257%2F4257367%2Foverlay_21665c2cb0e07eb23c68a01b7ec9b101.jpg&type=auto&width=500&sign=5-ROnVOl_jqBh9XQXSq9N-EgLqy08tCK4XVzPWHkx7c","l":"/go/p/U1bylNSG61Ej/2ace29e87/d4f678b43","b":"ASUS","m":"evomag.ro","c":"Laptopuri / Notebook","p":10999.99},{"t":"Laptop Gaming ASUS ROG Strix G18 G815LM (Procesor Intel® Core™ Ultra 9 275HX (36M Cache, up to 5.40 GHz), 18inch 2.5K 240Hz, 16GB DDR5, 1TB SSD, NVIDIA GeForce RTX 5060 @8GB, Negru/Gri)","i":"https://static2.evomag.ro/img?extend=white&file=products%2F4226%2F4226238%2Flaptop-gaming-asus-rog-strix-g-6811dbf665f8d.jpg&type=auto&width=500&sign=WT5s0NRRky4O0YvWRRLwx3K1WJQTMIV2ZBDjzwdp0FQ","l":"/go/p/jBKEJt5xrGCz/2ace29e87/d4f678b43","b":"ASUS","m":"evomag.ro","c":"Laptopuri / Notebook","p":10099.99},{"t":"Laptop Gaming ASUS ROG Strix G16 G615JMR (Procesor Intel® Core™ i9-14900HX (36M Cache, up to 5.80 GHz), 16inch  2.5K 240Hz, 16GB, 1TB SSD, NVIDIA GeForce RTX 5060 @8GB, Negru/Gri)","i":"https://static2.evomag.ro/img?extend=white&file=products%2F4226%2F4226050%2Flaptop-gaming-asus-rog-strix-g-683d9b161e34b.jpg&type=auto&width=500&sign=mqJ4EVmCL9wDu6-23hMoMyrZ1otnRFGmASzdBWpg1so","l":"/go/p/hx5JW007mPzp/2ace29e87/d4f678b43","b":"ASUS","m":"evomag.ro","c":"Laptopuri / Notebook","p":9399.99},{"t":"Laptop Gaming ASUS ROG Strix G16 G615LH (Procesor Intel® Core™ Ultra 7 255HX (30M Cache, up to 5.20 GHz), 16inch 2.5K 240Hz, 16GB, 512GB SSD, NVIDIA GeForce RTX 5050 @8GB, Negru/Gri)","i":"https://static2.evomag.ro/img?extend=white&file=products%2F4232%2F4232402%2Flaptop-gaming-asus-rog-strix-g-683d9b161e34b.jpg&type=auto&width=500&sign=F6HjbB8686MqmeQ6ufPt8ynbEl7AIx3iLeLZXOA6Gjw","l":"/go/p/QL5J_4rLx0W3/2ace29e87/d4f678b43","b":"ASUS","m":"evomag.ro","c":"Laptopuri / Notebook","p":8199.99},{"t":"Laptop Gaming ASUS TUF A16 FA608UH (Procesor AMD Ryzen™ 7 260 (16M Cache, up to 5.1 GHz), 16inch FHD+ 165Hz, 16GB DDR5, 512GB SSD, NVIDIA GeForce RTX 5050 @8GB, DLSS 3.0, Negru/Gri)","i":"https://static2.evomag.ro/img?extend=white&file=products%2F4232%2F4232355%2Flaptop-gaming-asus-tuf-a16-fa6-6863bdb72dbd5.jpg&type=auto&width=500&sign=TEBQiIWaZfZgwE3to5pwVOaXwcA2ludOa7MCovj_2Rk","l":"/go/p/8dk0v8eTJs3D/2ace29e87/d4f678b43","b":"ASUS","m":"evomag.ro","c":"Laptopuri / Notebook","p":5799.99},{"t":"Laptop Gaming ASUS TUF A16 FA607NUG (Procesor AMD Ryzen™  7 7445HS (16M Cache, up to 4.7 GHz), 16inch FHD+ 144Hz, 16GB, 512GB SSD, nVidia GeForce RTX 4050 @6GB, Negru/Gri)","i":"https://static2.evomag.ro/img?extend=white&file=products%2F4245%2F4245150%2Fas-16-r5-7535hs-16-512-4050-wu-6800ea11acc0e.jpg&type=auto&width=500&sign=NQIP3Cfz6429ACMtuvlMtmWLGvbw3bdO3sQ0sASWYwA","l":"/go/p/S_Au3a1Gf0OM/2ace29e87/d4f678b43","b":"ASUS","m":"evomag.ro","c":"Laptopuri / Notebook","p":4499.99},{"t":"Laptop Gaming ASUS TUF A15 FA506NCG (Procesor AMD Ryzen™ 7 7445HS (16M Cache, up to 4.7 GHz) 15.6inch FHD 144Hz, 16GB, 512GB SSD, nVidia GeForce RTX 3050 @4GB, Negru)","i":"https://static2.evomag.ro/img?extend=white&file=products%2F4240%2F4240530%2Flaptop-gaming-asus-tuf-a15-fa5-65d88b1113846.jpg&type=auto&width=500&sign=yv9QrqHvUc9rDbG4cXxG38p0Po6TdVofrJ-OqgEhjmI","l":"/go/p/YmQ0Vbw1j0RR/2ace29e87/d4f678b43","b":"ASUS","m":"evomag.ro","c":"Laptopuri / Notebook","p":3999.99},{"t":"Laptop Gaming ASUS ROG Strix SCAR 16 G635LX (Procesor Intel® Core™ Ultra 9 275HX (36M Cache, up to 5.40 GHz), 16inch 2.5K Mini LED 240Hz, 64GB, 2TB SSD, NVIDIA GeForce RTX 5090 @24GB, Win 11 Pro, Negru)","i":"https://static2.evomag.ro/img?extend=white&file=products%2F4228%2F4228318%2Flaptop-gaming-asus-rog-strix-s-683eee3ad8bdf.jpg&type=auto&width=500&sign=A1-RfVW7-temW07ke6sezrUiXmqKtPSEs1CQIFzQ_eM","l":"/go/p/nrk9vVg_nJir/2ace29e87/d4f678b43","b":"ASUS","m":"evomag.ro","c":"Laptopuri / Notebook","p":26599.99},{"t":"Laptop Gaming ASUS ROG Strix G18 G835LX (Procesor Intel® Core™ Ultra 9 275HX (36M Cache, up to 5.40 GHz), 18inch 2.5K Mini LED 240Hz, 64GB DDR5,   2TB SSD, NVIDIA GeForce RTX 5090 @24GB, Negru)","i":"https://static2.evomag.ro/img?extend=white&file=products%2F4219%2F4219366%2Flaptop-gaming-asus-rog-strix-g-6811e59d7e8b9.jpg&type=auto&width=500&sign=PjeJcU6fj9k8seuFnR85XF8duVgXodT9oDevpfXTNB4","l":"/go/p/b1d689a92/2ace29e87/d4f678b43","b":"ASUS","m":"evomag.ro","c":"Laptopuri / Notebook","p":26399.99},{"t":"Laptop Gaming ASUS ROG Strix G18 G835LX (Procesor Intel® Core™ Ultra 9 275HX (36M Cache, up to 5.40 GHz), 18inch 2.5K Mini LED 240Hz, 64GB DDR5, 2TB SSD, NVIDIA GeForce RTX 5090 @24GB, Negru)","i":"https://static2.evomag.ro/img?extend=white&file=products%2F4230%2F4230366%2Flaptop-gaming-asus-rog-strix-g-6811e59d7e8b9.jpg&type=auto&width=500&sign=Y34OTUF3LP6KlRslVX9ntWJVR452WW0cTulbCInGGF8","l":"/go/p/8qdbZlMK14-n/2ace29e87/d4f678b43","b":"ASUS","m":"evomag.ro","c":"Laptopuri / Notebook","p":26199.99},{"t":"Laptop Gaming ASUS ROG Strix SCAR 16 G635LX (Procesor Intel® Core™ Ultra 9 275HX (36M Cache, up to 5.40 GHz), 16inch 2.5K Mini LED 240Hz, 64GB, 2TB SSD, NVIDIA GeForce RTX 5090 @24GB, Negru)","i":"https://static2.evomag.ro/img?extend=white&file=products%2F4228%2F4228320%2Flaptop-gaming-asus-rog-strix-s-683eee3ad8bdf.jpg&type=auto&width=500&sign=-SN3OTXzTb4ucYePHENMAAk3go6a7yR646fnGRWUOdc","l":"/go/p/cytSbimEoVps/2ace29e87/d4f678b43","b":"ASUS","m":"evomag.ro","c":"Laptopuri / Notebook","p":25599.99},{"t":"Laptop Gaming Asus ROG Strix G16 G615LH-S5045, 16\" WQXGA, IPS, 16 GB RAM DDR5, 512 GB SSD, NVIDIA GeForce RTX 5050, Fara Sistem de operare, Eclipse Gray","i":"https://www.flanco.ro/media/catalog/product/6/9/69443769b94151acfdb1.59800767.jpeg","l":"/go/p/J3IwUj0atAEu/2ace29e87/ea7857c9c","b":"Asus","m":"flanco.ro","c":"Gaming Laptop","p":8735.99},{"t":"Laptop Gaming Asus TUF A18 FA808UH-S8073, 16\" WUXGA, IPS, AMD Ryzen 7 260, 32 GB RAM DDR5, 512 GB SSD, NVIDIA GeForce RTX 5050, Fara Sistem de operare, Gri","i":"https://www.flanco.ro/media/catalog/product/6/9/69448469b95c3ba00058.61106557.jpeg","l":"/go/p/9-nKs7FfSazP/2ace29e87/ea7857c9c","b":"Asus","m":"flanco.ro","c":"Gaming Laptop","p":7253.99},{"t":"Laptop Gaming Asus TUF Gaming F16 FX608JHR-RV125, 16\" WUXGA, IPS, 16 GB RAM DDR5, 512 GB SSD, NVIDIA GeForce RTX 5050, Fara Sistem de operare, Jaeger Gray","i":"https://www.flanco.ro/media/catalog/product/6/9/69443069b9404606fe83.91831376.jpeg","l":"/go/p/zZzVVWQpnPt_/2ace29e87/ea7857c9c","b":"Asus","m":"flanco.ro","c":"Gaming Laptop","p":6161.99},{"t":"Laptop Gaming Asus TUF Gaming A16 FA607NUG-RL150, 16\" WUXGA, IPS, 16 GB RAM DDR5, 512 GB SSD, NVIDIA GeForce RTX 4050, Fara Sistem de operare, Mecha Gray","i":"https://www.flanco.ro/media/catalog/product/6/9/69424769b832edec3619.24730408.jpeg","l":"/go/p/RtWMOiywWzFP/2ace29e87/ea7857c9c","b":"Asus","m":"flanco.ro","c":"Gaming Laptop","p":5196.99}]