[{"t": "Televizor Smart Blaupunkt 65UGC5500S, 165 cm, 4K, Google TV, Bluetooth, Wi-Fi, Clasa G", "i": "https://www.flanco.ro/media/catalog/product/b/l/blau_65ugc5500_front.jpg", "l": "/go/p/cf55dbf91/2ace29e87/ea7857c9c", "m": "flanco.ro", "p": 2999.99}, {"t": "Trotineta electrica Blaupunkt ESC90X, 350 W, Autonomie 40 Km, 20 Km/h, Negru", "i": "https://www.flanco.ro/media/catalog/product/t/r/trotineta_electrica_blaupunkt_esc90x_350_w_autonomie_40_km_negru.jpg", "l": "/go/p/dcd02ae80/2ace29e87/ea7857c9c", "m": "flanco.ro", "p": 2399.99}, {"t": "Boxa portabila Blaupunkt PB10DB, Karaoke, Bluetooth, Negru", "i": "https://www.flanco.ro/media/catalog/product/b/o/boxa_portabila_blaupunkt_pb10db_bluetooth_negru.jpg", "l": "/go/p/4ec5ab413/2ace29e87/ea7857c9c", "m": "flanco.ro", "p": 2089.99}, {"t": "Boxa portabila Blaupunkt cu Karaoke si Bluetooth PB12DB", "i": "https://static2.evomag.ro/img?extend=white&file=products%2F4077%2F4077080%2F63da2e6cef79b.jpg&type=auto&width=500&sign=Baypjh3OqhaQA-7trPYoYimikmxXoGcGcPYJm296yCU", "l": "/go/p/KRnLCYXwtxRQ/2ace29e87/d4f678b43", "m": "evomag.ro", "p": 2054.99}, {"t": "Televizor Smart Blaupunkt 55UGC5500S, 139 cm, 4K, Google TV, Bluetooth, Wi-Fi, Clasa G", "i": "https://www.flanco.ro/media/catalog/product/b/l/blau_55ugc5500_front.jpg", "l": "/go/p/b100bc6f1/2ace29e87/ea7857c9c", "m": "flanco.ro", "p": 1899.99}, {"t": "Boxa portabila profesionala Blaupunkt PS11DB, Bluetooth, Karaoke, Lumini LED, Negru/Albastru, 1200W", "i": "https://www.flanco.ro/media/catalog/product/b/o/boxa_portabila_blaupunkt_ps11db_karaoke_front.jpg", "l": "/go/p/b594a27b5/2ace29e87/ea7857c9c", "m": "flanco.ro", "p": 1799.99}, {"t": "Boxa profesionala Bluetooth FM/SD/USB/AUX/KARAOKE, 1900W, PA25", "i": "https://static2.evomag.ro/img?extend=white&file=products%2F3920%2F3920503%2F62398247e4a38.jpg&type=auto&width=500&sign=UEhoq83cf9bPeO6OBtuyQP23TAUjon2D8gJ20sQcAKs", "l": "/go/p/PWBifrNgq6Tg/2ace29e87/d4f678b43", "m": "evomag.ro", "p": 1550.99}, {"t": "Boxa portabila profesionala Blaupunkt PS6, Bluetooth, FM, SD, USB, Karaoke, Lumini LED, Negru", "i": "https://www.flanco.ro/media/catalog/product/1/4/147727-1_1.jpg", "l": "/go/p/2a88f07f5/2ace29e87/ea7857c9c", "m": "flanco.ro", "p": 1249.99}, {"t": "Boxa portabila profesionala Blaupunkt PA12, Bluetooth, Negru", "i": "https://www.flanco.ro/media/catalog/product/1/3/136080_1.jpg", "l": "/go/p/d55dcacd2/2ace29e87/ea7857c9c", "m": "flanco.ro", "p": 1229.99}, {"t": "Dezumidificator Blaupunkt ADH701, 20 L, Functie ionizare, Recomandat pana la 45 mp (Alb)", "i": "https://static2.evomag.ro/img?extend=white&file=products%2F3818%2F3818370%2Fadh701-60d9741433859.JPG&type=auto&width=500&sign=B4pMdMZ6Anh3GG0W2J-3Tq_IUKnmuo-TOyXyKD1DWA0", "l": "/go/p/43UiFFg3minB/2ace29e87/d4f678b43", "m": "evomag.ro", "p": 1133.99}, {"t": "Boxa portabila Blaupunkt MB08.2, Bluetooth, Karaoke, 600W, Negru/Albastru", "i": "https://www.flanco.ro/media/catalog/product/b/o/boxa_portabila_blaupunkt_mb08.2_front.jpg", "l": "/go/p/341e8d358/2ace29e87/ea7857c9c", "m": "flanco.ro", "p": 1079.99}, {"t": "Dezumidificator Blaupunkt ADH601, capacitate de dezumidificare 16l/zi", "i": "https://static2.evomag.ro/img?extend=white&file=products%2F4149%2F4149236%2F65facdb11ae0c.jpg&type=auto&width=500&sign=qPL3dccxTerPNhC0sO5PKCAXgdA2dj6DTuT-VQqMG2o", "l": "/go/p/aj3YJOaSs6xO/2ace29e87/d4f678b43", "m": "evomag.ro", "p": 1032.99}, {"t": "Boxa portabila profesionala Blaupunkt PA10, 38W, Bluetooth, FM, SD, USB, AUX, Karaoke", "i": "https://www.flanco.ro/media/catalog/product/1/4/147721-1.jpg", "l": "/go/p/7d98d4146/2ace29e87/ea7857c9c", "m": "flanco.ro", "p": 1029.99}, {"t": "Dezumidificator Blaupunkt ADH501, 16 L, Functie ionizare, Recomandat pana la 45 mp (Alb)", "i": "https://static2.evomag.ro/img?extend=white&file=products%2F3818%2F3818369%2Fadh501-60d9719354ca4.JPG&type=auto&width=500&sign=-UW8kUknQsh2-BXoaokqtpM1MblsWEDFQFOhapLKozU", "l": "/go/p/LknYYzFIYaHN/2ace29e87/d4f678b43", "m": "evomag.ro", "p": 927.99}, {"t": "Boxa portabila Blaupunkt, MB06, Bluetooth, FM/SD/USB/AUX/KARAOKE, 500W", "i": "https://static2.evomag.ro/img?extend=white&file=products%2F3881%2F3881088%2F623982518a4f1.jpg&type=auto&width=500&sign=WNg6lPZ4Q3jneEJIO9tL6VJoENtkoc88oHvH4qbi9FY", "l": "/go/p/6772c39e1/2ace29e87/d4f678b43", "m": "evomag.ro", "p": 652.99}, {"t": "Cuptor electric Blaupunkt EOM601, 1800 W, 45 L, Rotisor, Convectie (Negru)", "i": "https://static2.evomag.ro/img?extend=white&file=products%2F3818%2F3818778%2Feom601-60dda596a1fc0.JPG&type=auto&width=500&sign=ey2mOUC3QbVujHgYV9DNFm5RoapLdrsNCtEX_x1n28I", "l": "/go/p/nFidV2A-e4h9/2ace29e87/d4f678b43", "m": "evomag.ro", "p": 646.99}, {"t": "Microsistem Blaupunkt MS45BT, 100W, Bluetooth, CD, MP3, USB, Alb", "i": "https://static2.evomag.ro/img?extend=white&file=products%2F3871%2F3871211%2F623819fd10c40.jpg&type=auto&width=500&sign=KLonpvqvptrrEJGOxbeOmO6g68eZeFAmhczoqfk-Ui4", "l": "/go/p/3e4252931/2ace29e87/d4f678b43", "m": "evomag.ro", "p": 638.99}, {"t": "Umidificator de aer Blaupunkt AHE601,Rezervor 4l,Filtru antibacterian cu ioni de argint", "i": "https://static2.evomag.ro/img?extend=white&file=products%2F3870%2F3870324%2F62381969a9aca.png&type=auto&width=500&sign=ivvl8GAzVrl8SKCtioeRJxU2CPrP7burwtZbEaV7ZD8", "l": "/go/p/EcseFSz7Y5I0/2ace29e87/d4f678b43", "m": "evomag.ro", "p": 544.99}, {"t": "Umidificator de aer Blaupunkt AHS801, 5 L, 400 ml/h, Display LCD (Argintiu/Negru)", "i": "https://static2.evomag.ro/img?extend=white&file=products%2F3818%2F3818367%2Fahs801-60d96f21398b4.JPG&type=auto&width=500&sign=zjzyDa0g8VYzzWaIecFk-j7rJiWIEkMeZslTK4I9D4Y", "l": "/go/p/1fvF6cqfhRMr/2ace29e87/d4f678b43", "m": "evomag.ro", "p": 518.99}, {"t": "Umidificator Blaupunkt AHM701, 400 W, 5 L (Alb/Negru)", "i": "https://static2.evomag.ro/img?extend=white&file=products%2F4075%2F4075226%2Fblaupunkt-air-humidifier-ahm70-63c7c35863acf.JPG&type=auto&width=500&sign=l7Z7xfU2gqwPKKExVvsUC9VcWTWjPop2wnVz84sVpCc", "l": "/go/p/dac3a26aa/2ace29e87/d4f678b43", "m": "evomag.ro", "p": 458.99}, {"t": "Mop cu abur Blaupunkt STM601, 1500W, 0.36 L (Alb)", "i": "https://static2.evomag.ro/img?extend=white&file=products%2F4112%2F4112105%2F64c7b3fe26989.jpg&type=auto&width=500&sign=-8e9dMebcDc2SJlt41iDNOVyZv3nNEu9YU7Gmjxd-oQ", "l": "/go/p/1afe3511c/2ace29e87/d4f678b43", "m": "evomag.ro", "p": 432.99}, {"t": "Radio portabil Boombox Blaupunkt BB31LED, Bluetooth, FM, MP3, AUX, USB, Ceas cu alarma", "i": "https://static2.evomag.ro/img?extend=white&file=products%2F3925%2F3925130%2F62397d0f55cdf.jpeg&type=auto&width=500&sign=to4250cd_Wtqi5MMTpjxlxpc28KiV7JrH72SmXaNwgE", "l": "/go/p/d552a96e3/2ace29e87/d4f678b43", "m": "evomag.ro", "p": 431.99}, {"t": "Umidificator de aer Blaupunkt AHS601, 4.5 L, Display LCD (Alb/Negru)", "i": "https://static2.evomag.ro/img?extend=white&file=products%2F3818%2F3818365%2Fahs601-60d96c8e47708.JPG&type=auto&width=500&sign=VWBHxCqwnpIMxLPw-2N8D0yCRH8-iAMT2CrubzvNCzY", "l": "/go/p/faf1261db/2ace29e87/d4f678b43", "m": "evomag.ro", "p": 427.99}, {"t": "Robot de bucatarie Blaupunkt SMM501", "i": "https://static2.evomag.ro/img?extend=white&file=products%2F3931%2F3931615%2F628b5ffad8761.JPG&type=auto&width=500&sign=6jzMyc98kSY_EUu57cP2Ao2QkpQBODHF9qaTg_3cBdE", "l": "/go/p/48d0dffd7/2ace29e87/d4f678b43", "m": "evomag.ro", "p": 426.99}, {"t": "Boxa portabila Blaupunkt BT08LED, 5 W, FM, microSD, USB, AUX, LED", "i": "https://www.flanco.ro/media/catalog/product/b/o/boxa_blaupunkt_bt08led_main.jpg", "l": "/go/p/ca5219aa6/2ace29e87/ea7857c9c", "m": "flanco.ro", "p": 349.99}, {"t": "Radio cu ceas Blaupunkt CR85BK CHARGE, Wireless Charging", "i": "https://www.flanco.ro/media/catalog/product/1/4/147718-1.jpg", "l": "/go/p/cdd7392fd/2ace29e87/ea7857c9c", "m": "flanco.ro", "p": 319.99}, {"t": "Radiator ulei 7 elementi 1500W Blaupunkt HOR301, termostat reglabil, protectie la supraincalzire", "i": "https://static2.evomag.ro/img?extend=white&file=products%2F3871%2F3871130%2F62381bf74a8ee.jpg&type=auto&width=500&sign=hiPeKlP7jHY7qdzc4SXFL00xofHHUP47_aRmQ6i9_Wc", "l": "/go/p/RId2XvbNoSUP/2ace29e87/d4f678b43", "m": "evomag.ro", "p": 307.99}, {"t": "Masina de tocat carne Blaupunkt FMM401", "i": "https://static2.evomag.ro/img?extend=white&file=products%2F3871%2F3871134%2F6238183e7c405.jpg&type=auto&width=500&sign=U0D6vY_HCYm_SxJEOAXrocqt8-YyDSNlnhaRN3ZYooM", "l": "/go/p/ba3257573/2ace29e87/d4f678b43", "m": "evomag.ro", "p": 290.99}, {"t": "Boxa portabila Blaupunkt BT11ALU, Bluetooth, Gri", "i": "https://www.flanco.ro/media/catalog/product/b/o/boxa_portabila_blaupunkt_bt11alu_bluetooth_gri.jpg", "l": "/go/p/19894a8f9/2ace29e87/ea7857c9c", "m": "flanco.ro", "p": 279.99}, {"t": "Geanta ghidon Blaupunkt ACE800 pentru trotineta electrica Blaupunkt ESC808 (Negru)", "i": "https://static2.evomag.ro/img?extend=white&file=products%2F4083%2F4083889%2Fgeanta-ghidon-blaupunkt-ace800-640b17427b7c6.jpg&type=auto&width=500&sign=CX_QDHlhi7Ta3RGrpGjs5btv_u9f1kVO9IYogpAOgO8", "l": "/go/p/b21b8066b/2ace29e87/d4f678b43", "m": "evomag.ro", "p": 277.99}, {"t": "Aspirator cu sac Blaupunkt VCB201, 2 L, 700 W (Alb/Gri)", "i": "https://static2.evomag.ro/img?extend=white&file=products%2F3818%2F3818510%2Fvcb201-60dabcfca9eed.JPG&type=auto&width=500&sign=hG-dXD4nC1GkNtGJZ41CUsvpz2e2cZzMyMt-77cevmE", "l": "/go/p/eb4bda0dc/2ace29e87/d4f678b43", "m": "evomag.ro", "p": 275.99}, {"t": "Ceas cu radio Blaupunkt CR12WH, Termometru, Alb", "i": "https://static2.evomag.ro/img?extend=white&file=products%2F3871%2F3871205%2F6238139239f2a.jpg&type=auto&width=500&sign=AzLn_H1fseCPxZphV583xrC0p6DKJyX-F2xTlAfa4uE", "l": "/go/p/c1801b4ba/2ace29e87/d4f678b43", "m": "evomag.ro", "p": 247.99}, {"t": "Ceas cu radio Blaupunkt CR12BK, Termometru, Negru", "i": "https://static2.evomag.ro/img?extend=white&file=products%2F3873%2F3873559%2F6239801d12c78.jpg&type=auto&width=500&sign=GpvVWrc3rqb3D-sigCSrp4G0LNlL2tW6penTmkZdu_0", "l": "/go/p/snExF8pu9fF7/2ace29e87/d4f678b43", "m": "evomag.ro", "p": 246.99}, {"t": "Irigator bucal Blaupunkt DIR501, 150 ml (Alb/Albastru)", "i": "https://static2.evomag.ro/img?extend=white&file=products%2F3819%2F3819426%2Fdir501-60e6de22671cc.JPG&type=auto&width=500&sign=OY60hy1T3a3L1ZFfAqN4CyNSWnx0w2bVbdpV5p6q2Dk", "l": "/go/p/J68o1zrorejG/2ace29e87/d4f678b43", "m": "evomag.ro", "p": 243.99}, {"t": "Radio cu ceas Blaupunkt CR55CHARGE, FM, Incarcator USB, Incarcator wireless, Negru", "i": "https://www.flanco.ro/media/catalog/product/1/4/147725-1.jpg", "l": "/go/p/42a6f76a0/2ace29e87/ea7857c9c", "m": "flanco.ro", "p": 229.99}, {"t": "Radio cu ceas Blaupunkt CRP7WH, Proiector, USB (Alb)", "i": "https://static2.evomag.ro/img?extend=white&file=products%2F3881%2F3881628%2Fceas-cu-radio-blaupunkt-crp7wh-6242b2b3bf574.PNG&type=auto&width=500&sign=0hNY5N_R002DbjQz8TOuQc7OsYP-TN7QBqPZwlyBlcI", "l": "/go/p/4767bf000/2ace29e87/d4f678b43", "m": "evomag.ro", "p": 220.99}, {"t": "Umidificator de aer Blaupunkt AHS301, 3.5 L, 300 ml/h, Ultrasonic, Ionizare, Aromaterapie (Alb/Roz)", "i": "https://static2.evomag.ro/img?extend=white&file=products%2F3818%2F3818366%2Fahs301-60d96dd157252.JPG&type=auto&width=500&sign=qJ32yFAoTNoXGb57tdYYstcuwVcFuP72gonhB0Fz3Fs", "l": "/go/p/dXNO-MpjqS8n/2ace29e87/d4f678b43", "m": "evomag.ro", "p": 220.98}, {"t": "Masina de tocat carne Blaupunkt FMM301, 1300 W, 1.5 Kg/min (Alb)", "i": "https://static2.evomag.ro/img?extend=white&file=products%2F4149%2F4149297%2F65faccf714df5.png&type=auto&width=500&sign=dgLWEYss0PYIYFtrXI4f3I-9iAzYsLjZ_V2vd0t21sA", "l": "/go/p/687b06636/2ace29e87/d4f678b43", "m": "evomag.ro", "p": 217.99}, {"t": "Radio cu ceas Blaupunkt CR10ALU, FM radio, Dual Alarm, Senzor intern de temperatura si umiditate incorporat", "i": "https://static2.evomag.ro/img?extend=white&file=products%2F4111%2F4111090%2F64c84f17663fe.jpg&type=auto&width=500&sign=pPDqiLcauj_MdRrpPWHZW1dfN18O06EDQYfeUyYzdzA", "l": "/go/p/tZnbfn62tCbH/2ace29e87/d4f678b43", "m": "evomag.ro", "p": 199.99}, {"t": "Geanta transport Blaupunkt ACE700 pentru trotinete electrice, 110 x 45 x 50 cm (Negru)", "i": "https://static2.evomag.ro/img?extend=white&file=products%2F4083%2F4083890%2Fgeanta-transport-blaupunkt-ace-640b182b8ce0a.jpg&type=auto&width=500&sign=wjvTqlvFVXmZHIhtjovoag0btyjhWHw2_Ii8JrQp1cQ", "l": "/go/p/c18f4806e/2ace29e87/d4f678b43", "m": "evomag.ro", "p": 195.99}, {"t": "Cafetiera Blaupunkt CMD802WH, 1.5 L, 900 W, Oprire automata (Argintiu)", "i": "https://static2.evomag.ro/img?extend=white&file=products%2F4148%2F4148976%2F65f832a57780c.png&type=auto&width=500&sign=75RqwmB1KvL81S5Ke6NbXdXGTL-xASoXYZvAllw8hRg", "l": "/go/p/cRz5KvV1p7bx/2ace29e87/d4f678b43", "m": "evomag.ro", "p": 189.99}, {"t": "Radio portabil Blaupunkt FM/BT/USB/AUX PP7BT", "i": "https://static2.evomag.ro/img?extend=white&file=products%2F4125%2F4125510%2F6536416e1b599.jpg&type=auto&width=500&sign=t7OgD4UVZro6WgKP-0zRoASPgQNlvmJw6pFWWXiUbk0", "l": "/go/p/b03258f9d/2ace29e87/d4f678b43", "m": "evomag.ro", "p": 180.99}, {"t": "Radio portabil Blaupunkt PP5.2BR, Maro", "i": "https://static2.evomag.ro/img?extend=white&file=products%2F4099%2F4099544%2F64899ae7909bc.jpg&type=auto&width=500&sign=tkGGPgZklMIXBsyuGzyXZcblGI0FrnLCZ-XbR8YbQZk", "l": "/go/p/cd93f5c77/2ace29e87/d4f678b43", "m": "evomag.ro", "p": 180.99}, {"t": "Radio cu ceas Blaupunkt CR6SL, FM, Argintiu", "i": "https://www.flanco.ro/media/catalog/product/c/r/cr6sl_1.jpg", "l": "/go/p/15e102fbc/2ace29e87/ea7857c9c", "m": "flanco.ro", "p": 179.99}, {"t": "Radio cu ceas Blaupunkt CRP9BK, FM radio, Dual Alarm, Termometru, Proiector, USB, Negru", "i": "https://static2.evomag.ro/img?extend=white&file=products%2F3873%2F3873558%2F62398013410b6.jpg&type=auto&width=500&sign=ueLRxQ99Vnn8NVPV0yWiCo5i0Ga0Tl8UkNu4UN5xW3Q", "l": "/go/p/e29148465/2ace29e87/d4f678b43", "m": "evomag.ro", "p": 173.99}, {"t": "Radio cu ceas Blaupunkt CR7BK", "i": "https://static2.evomag.ro/img?extend=white&file=products%2F1373%2F1373665%2F1443434712Radio+cu+ceas+Blaupunkt+CR7BK.jpg&type=auto&width=500&sign=mV7CjsZLK-dl6Z9p32WoyllSI8JjpjmoGQ-GnwfYZyo", "l": "/go/p/7TVW2xpDegAm/2ace29e87/d4f678b43", "m": "evomag.ro", "p": 169.99}, {"t": "Radio cu ceas Blaupunkt CR80USB, FM, incarcator USB, indicator temperatura", "i": "https://static2.evomag.ro/img?extend=white&file=products%2F3873%2F3873565%2F62397b6ae02cd.jpg&type=auto&width=500&sign=04LwOQv1R5qvhEtZmIfWp9CFTgUQ4RJW6cGHB1RHRAg", "l": "/go/p/7jCSCFaf7IaJ/2ace29e87/d4f678b43", "m": "evomag.ro", "p": 168.99}, {"t": "Radio cu ceas Blaupunkt PP5BR, slot microSD, USB, telecomanda (Maro)", "i": "https://static2.evomag.ro/img?extend=white&file=products%2F1373%2F1373651%2F1443164534Radio+cu+ceas+Blaupunkt+PP5BR%2C+slot+microSD%2C+USB%2C+telecomanda+%28Maro%29.jpg&type=auto&width=500&sign=zW-Y_aMQpfcTwvMfgOrSHwc6JW1xveJwQldWtBS_f-Q", "l": "/go/p/c66cf547b/2ace29e87/d4f678b43", "m": "evomag.ro", "p": 163.99}, {"t": "Cafetiera Blaupunkt CMD401, 800 W, 1.25 L, Timer (Negru/Argintiu)", "i": "https://static2.evomag.ro/img?extend=white&file=products%2F3819%2F3819355%2Fcmd401-60e6a1b898adb.JPG&type=auto&width=500&sign=3Y88aMSQd3trEyZ6UIHVM1hFycPf_PQIienWnKXcJ1g", "l": "/go/p/lT23GXeBXpe_/2ace29e87/d4f678b43", "m": "evomag.ro", "p": 150.99}, {"t": "Radio cu ceas Blaupunkt CR7USB, USB, Negru", "i": "https://www.flanco.ro/media/catalog/product/c/r/cr7usb_1.jpg", "l": "/go/p/1d73b9a6a/2ace29e87/ea7857c9c", "m": "flanco.ro", "p": 149.99}, {"t": "Radio portabil Blaupunkt, PR5BL, MicroSD/USB/MP3, Afisaj LCD, AAA, Negru/Albastru", "i": "https://static2.evomag.ro/img?extend=white&file=products%2F3873%2F3873562%2F6239800812918.jpg&type=auto&width=500&sign=HHUZxhq207sRX3D3ES4XX0tKii7F9gZFoEpqE_uA8gI", "l": "/go/p/0XQ8XYu8upwz/2ace29e87/d4f678b43", "m": "evomag.ro", "p": 146.99}, {"t": "Radio cu ceas Blaupunkt CR16WH, FM radio, Dual Alarm, USB, Alb", "i": "https://static2.evomag.ro/img?extend=white&file=products%2F3873%2F3873561%2Fradio-cu-ceas-blaupunkt-cr16wh-642cfe7538f63.JPG&type=auto&width=500&sign=x3ob4V6y2qHHzMpKbZZLzJn70IX0Oo9R-KF9nnPI23o", "l": "/go/p/301902084/2ace29e87/d4f678b43", "m": "evomag.ro", "p": 145.99}, {"t": "Aparat popcorn Blaupunkt FPC401, 1200W, cana de masura, 2-4 min pentru o portie, preparare fara ulei sau grasimi", "i": "https://static2.evomag.ro/img?extend=white&file=products%2F3927%2F3927674%2F62397effcb73f.png&type=auto&width=500&sign=JMQVCKwBm0ZqNM4LFXqIUnfjK2a7I3bT5Y7oOXIrkfs", "l": "/go/p/5943b13c0/2ace29e87/d4f678b43", "m": "evomag.ro", "p": 140.99}, {"t": "Boxa portabila Blaupunkt BT05BL, Bluetooth, FM radio, SD, USB, baterie 1500mAh, Albastru", "i": "https://www.flanco.ro/media/catalog/product/b/l/blaupunkt_bt05bl_1.jpg", "l": "/go/p/d55f020a2/2ace29e87/ea7857c9c", "m": "flanco.ro", "p": 129.99}, {"t": "Cantar de baie Blaupunkt, Negru", "i": "https://static2.evomag.ro/img?extend=white&file=products%2F4148%2F4148895%2F65f836870e1c1.jpg&type=auto&width=500&sign=YsU4rsa_nQkAiM349w5NsMVN-AxPwkSEECQJhRk9mMM", "l": "/go/p/CuAeIQQGbHDQ/2ace29e87/d4f678b43", "m": "evomag.ro", "p": 123.99}, {"t": "Fierbator Blaupunkt EKG301, 1630W, 1L, Alb, baza rotativa, iluminare LED", "i": "https://static2.evomag.ro/img?extend=white&file=products%2F3870%2F3870283%2F62381a8d673a3.jpg&type=auto&width=500&sign=2Ab00iFGBNe-IQVDMPfWClNAcqoNB_EmxSf_JYanBSM", "l": "/go/p/90d5ecc71/2ace29e87/d4f678b43", "m": "evomag.ro", "p": 122.99}, {"t": "Rasnita de cafea Blaupunkt FCG701, 200 W, 85 g (Argintiu)", "i": "https://static2.evomag.ro/img?extend=white&file=products%2F3819%2F3819356%2Ffcg701-60e6a27a9fe09.JPG&type=auto&width=500&sign=Ts3b2_hqM0lTVxzG0SUGe34dkuaIBrK16MQS5HvsCOA", "l": "/go/p/cd0e60fcb/2ace29e87/d4f678b43", "m": "evomag.ro", "p": 121.99}, {"t": "Cantar de bucatarie cu bol de otel Blaupunkt FKS602", "i": "https://static2.evomag.ro/img?extend=white&file=products%2F3870%2F3870520%2F623878a276394.JPG&type=auto&width=500&sign=Rb4wI7PPuluhsmWo7FzWaw7Df-TzQMZ6VxMy-W6-32U", "l": "/go/p/a1a9cab85/2ace29e87/d4f678b43", "m": "evomag.ro", "p": 102.99}, {"t": "Cantar de bucatarie Blaupunkt FKS601, 5kg, Touch, 2 X AAA (Alb)", "i": "https://static2.evomag.ro/img?extend=white&file=products%2F3819%2F3819414%2Ffks601-60e6d20d2521d.JPG&type=auto&width=500&sign=VoDpd_U6R9vnY09isQS9QPf5xEtT_YQ2iEmqkC7NBUw", "l": "/go/p/mOMMCYFDBNV-/2ace29e87/d4f678b43", "m": "evomag.ro", "p": 93.99}, {"t": "Cantar de bucatarie Blaupunkt FKS501, 5kg, Touch, 2 X AAA, Vas inclus (Alb)", "i": "https://static2.evomag.ro/img?extend=white&file=products%2F3819%2F3819413%2Ffks501-60e6ce05e4ed0.JPG&type=auto&width=500&sign=zpoRXb4QQThRhMvTjLfQNxWLd9anPTGqEhXQI8GAvYk", "l": "/go/p/883dab62f/2ace29e87/d4f678b43", "m": "evomag.ro", "p": 73.99}]