[{"t": "Docking Station Satechi ST-UCT4DM-EU, 3x Thunderbolt 4, 40 Gbps, 96 W, 4K 60Hz, UHS-II SD, Jack 3.5 mm (Gri)", "i": "https://static2.evomag.ro/img?extend=white&file=products%2F4158%2F4158557%2Fsatechi-tbt4-2-103207.png&type=auto&width=500&sign=rzC0MRUHjsV78OF2NwnaWWwsjQspCbL34UbfmjHqvGM", "l": "/go/p/c5d4b40a2/2ace29e87/d4f678b43", "m": "evomag.ro", "p": 1783.99}, {"t": "Statie de andocare pentru trei ecrane 4K Satechi - Hub pentru 3 monitoare pentru Mac M1 si M2, Gri inchis", "i": "https://static2.evomag.ro/img?extend=white&file=products%2F4116%2F4116226%2F64f72828dfa3d.jpg&type=auto&width=500&sign=EF7dS7C5L3sjaMXkRE9xcLUPlJcEFFOysOdYB5zkKkw", "l": "/go/p/752a1f60d/2ace29e87/d4f678b43", "m": "evomag.ro", "p": 1191.99}, {"t": "HUB USB Satechi Slim Hub, Thunderbolt 4, 8K 30Hz (Gri)", "i": "https://static2.evomag.ro/img?extend=white&file=products%2F4099%2F4099008%2F64802de6145b4.jpg&type=auto&width=500&sign=uWzmwtDOoJJH89g0KKnABmKtgSaZsyk-H-vat_MF5KE", "l": "/go/p/4ca7bce47/2ace29e87/d4f678b43", "m": "evomag.ro", "p": 1048.99}, {"t": "HUB USB Satechi Slim Hub Pro ST-HT4SHM-EU, 96 W, 3x Thunderbolt 4 40Gbps, 15 W, 8K (Argintiu)", "i": "https://static2.evomag.ro/img?extend=white&file=products%2F4205%2F4205732%2Fsatechi-thunderbolt-4-slim-hub-67b5baa270811.jpeg&type=auto&width=500&sign=TxPPwHGZIdNnQobVvdSEnMI77oHw1yCPq5-oJyLbDEQ", "l": "/go/p/8df1b283e/2ace29e87/d4f678b43", "m": "evomag.ro", "p": 999.99}, {"t": "Statie de andocare Satechi ST-DDSM, cu carcasa SSD NVMe", "i": "https://static2.evomag.ro/img?extend=white&file=products%2F4130%2F4130292%2F655c6de7b64b9.png&type=auto&width=500&sign=FrBinK7cAzDzgz36-huYtgbW_RD78a-p3GcMWmkxYRQ", "l": "/go/p/Us0Doh8FgOCU/2ace29e87/d4f678b43", "m": "evomag.ro", "p": 870.99}, {"t": "HUB USB Satechi ST-UCM1HM, USB-C, M1 (Gri)", "i": "https://static2.evomag.ro/img?extend=white&file=products%2F4099%2F4099003%2F64802de0e4508.png&type=auto&width=500&sign=43L6UEjUIDnwbdsuq3YRRT-uAUgoVGq0XqbfIRvPwUI", "l": "/go/p/hUBzKH6adiL1/2ace29e87/d4f678b43", "m": "evomag.ro", "p": 665.99}, {"t": "Stand si hub Satechi ST-GMMSHS pentru Mac Mini / Studio cu carcasa SSD NVMe (Argintiu)", "i": "https://static2.evomag.ro/img?extend=white&file=products%2F4179%2F4179896%2Fstand-si-hub-satechi-st-gmmshs-66d5a7ccedb17.png&type=auto&width=500&sign=IaiZvEvyGBuSUbFU-QECiz1y9PB1n4xHCyAWNn1llEA", "l": "/go/p/219cfac8a/2ace29e87/d4f678b43", "m": "evomag.ro", "p": 548.99}, {"t": "Carcasa pemtru memorie externa Satechi USB4 NVMe SSD Satechi Pro Enclosure, Gri", "i": "https://static2.evomag.ro/img?extend=white&file=products%2F4147%2F4147458%2F65f0593a53ae7.jpg&type=auto&width=500&sign=9aycQuADBQpyeiNWKN89xzfOfNKS7xMEpq5jWV2o4i8", "l": "/go/p/01c28d67b/2ace29e87/d4f678b43", "m": "evomag.ro", "p": 528.99}, {"t": "HUB USB Satechi ST-P3D13K USB-C, Multiport 13-in-1 Triple, 4K/60Hz DisplayPort, USB-C PD 100 W(Negru)", "i": "https://static2.evomag.ro/img?extend=white&file=products%2F4285%2F4285262%2F69a597ddd7513.jpg&type=auto&width=500&sign=S9NoZKO1htSl_L984UZOnQP5EC7D9OPQj8X9PRzaimM", "l": "/go/p/yls876M2h5B9/2ace29e87/d4f678b43", "m": "evomag.ro", "p": 488.99}, {"t": "Acumulator extern Satechi Quatro Wireless, 10000 mAh (Negru)", "i": "https://static2.evomag.ro/img?extend=white&file=products%2F3850%2F3850099%2F62174a70011d7.jpg&type=auto&width=500&sign=d2GcpzXkCODADlKSOgf2AyXk47MGFWG6cfUSojYWcHk", "l": "/go/p/37a75e68c/2ace29e87/d4f678b43", "m": "evomag.ro", "p": 488.99}, {"t": "Adaptor Multimedia Satechi ST-TCMA2S, Type-C (Argintiu)", "i": "https://static2.evomag.ro/img?extend=white&file=products%2F3779%2F3779001%2F1577716214Adaptor+Multimedia+Satechi+ST-TCMA2S%2C+Type-C+%28Argintiu%291.jpg&type=auto&width=500&sign=RinZNec7nCUetOtm53D4mMeHfinAoMW3eanm7xj4ElM", "l": "/go/p/9e7b278bd/2ace29e87/d4f678b43", "m": "evomag.ro", "p": 477.99}, {"t": "Suport Satechi si Hub pentru Mac, Mini, M4 cu slot SSD ST-GNMMES (Alb)", "i": "https://static2.evomag.ro/img?extend=white&file=products%2F4285%2F4285246%2F69a597f5199b8.jpg&type=auto&width=500&sign=8ncmvvB2uoAMndbsDp1m6-jS4zbUNAl0F8xfQPGC0A0", "l": "/go/p/LUu1hbEk2qkI/2ace29e87/d4f678b43", "m": "evomag.ro", "p": 475.99}, {"t": "Hub USB cu incarcare Satechi ST-W145GTM, 145 W, 4 Porturi USB-C GaN (Gri)", "i": "https://static2.evomag.ro/img?extend=white&file=products%2F4158%2F4158403%2Fst-w145gtm-01.jpg&type=auto&width=500&sign=hEoZV8laUCh3QXH6LiYhqy4GoGB2UVhXfOPg3Wyyw9o", "l": "/go/p/aa04c8190/2ace29e87/d4f678b43", "m": "evomag.ro", "p": 470.99}, {"t": "Docking station Satechi Aluminium TYPE-C PRO Hub, ThunderBolt 3, Space Grey", "i": "https://static2.evomag.ro/img?extend=white&file=products%2F3848%2F3848604%2F62174accb9d5c.jpg&type=auto&width=500&sign=wGPzV3T3195jy7fE_tI5N0rHzo5QNAvDZ1VbBLakjzo", "l": "/go/p/47a8bb528/2ace29e87/d4f678b43", "m": "evomag.ro", "p": 418.99}, {"t": "Carcasa SSD Satechi USB4 NVMe pentru Mac mini, 40 Gbps, 8 TB, 2280/2260/2242/2230 mm (Gri)", "i": "https://static2.evomag.ro/img?extend=white&file=products%2F4285%2F4285260%2F69a597f86993a.jpg&type=auto&width=500&sign=rDBigDSso4f_7agmAxdjOqGsuIlMvUywHOZlWzvSHCE", "l": "/go/p/38xN8w18jppV/2ace29e87/d4f678b43", "m": "evomag.ro", "p": 414.99}, {"t": "HUB USB Multiport Satechi ST-P8KES, USB-C PD 100 W, 5x USB Type-C, HDMI 8K, Ethernet V3 (Argintiu)", "i": "https://static2.evomag.ro/img?extend=white&file=products%2F4205%2F4205729%2Fsatechi-usb-c-multiport-adapte-67b5b905dd4c2.jpg&type=auto&width=500&sign=pKzq8jNGCJNQn2k0aJuPUlEDMiUJC42zYn-nJiIGgOI", "l": "/go/p/f6a76ae6d/2ace29e87/d4f678b43", "m": "evomag.ro", "p": 406.99}, {"t": "Docking Station Satechi ST-TCMA2M, Type-C (Gri)", "i": "https://static2.evomag.ro/img?extend=white&file=products%2F3779%2F3779000%2F1577716067Adaptor+Multimedia+Satechi+ST-TCMA2M%2C+Type-C+%28Gri%291.jpg&type=auto&width=500&sign=Jb9r2iF9OhVlft1LomLEZD1ySSVs_hB0MHCwx42bd3Q", "l": "/go/p/5d55864ca/2ace29e87/d4f678b43", "m": "evomag.ro", "p": 406.99}, {"t": "Acumulator extern Satechi ST-B10Q2SR, 10000mAh cu suport, Wireless, 15 W (Bej)", "i": "https://static2.evomag.ro/img?extend=white&file=products%2F4285%2F4285225%2F69a597ecc069d.jpg&type=auto&width=500&sign=9G3ORJYQ1_1jJD3oPZlZv_Q2fG9IDADrZJBeFo4USBU", "l": "/go/p/MzLElZnWpcOk/2ace29e87/d4f678b43", "m": "evomag.ro", "p": 406.99}, {"t": "Docking station Satechi Aluminum TYPE-C pentru Mac Mini, Space Grey", "i": "https://static2.evomag.ro/img?extend=white&file=products%2F3848%2F3848609%2F62174a7d2225c.jpg&type=auto&width=500&sign=x_ysGBDvao8fvwo8bCf-cfOvMaaEkms1tbMtYgH2mtY", "l": "/go/p/790b44514/2ace29e87/d4f678b43", "m": "evomag.ro", "p": 376.99}, {"t": "Acumulator extern Satechi ST-B10Q2SK, 10000mAh, Wireless 15 W (Negru)", "i": "https://static2.evomag.ro/img?extend=white&file=products%2F4285%2F4285224%2F69a597ee169b8.jpg&type=auto&width=500&sign=s4cyi_SJSqeL3lHU07_Faam1bYdY2dmJF-OM0_6geSI", "l": "/go/p/xmzgI1VStkiu/2ace29e87/d4f678b43", "m": "evomag.ro", "p": 374.99}, {"t": "Acumulator extern Satechi 10000mAh cu suport, Wireless, 15 W (Alb)", "i": "https://static2.evomag.ro/img?extend=white&file=products%2F4285%2F4285226%2F69a597f57a32e.jpg&type=auto&width=500&sign=jIhrkzASeoIdKQj3xSEUq6KprJBuT0KR8ZG6apAwEw0", "l": "/go/p/xR0JBT_MILxk/2ace29e87/d4f678b43", "m": "evomag.ro", "p": 372.99}, {"t": "Stand si Hub Satechi pentru iPad Pro, USB-C, Space Gray", "i": "https://static2.evomag.ro/img?extend=white&file=products%2F3852%2F3852179%2F62174ab28707e.jpg&type=auto&width=500&sign=BdOwNgLBXWdkb0MZtf8MBcOqns68uEn40pvI7bw2vbk", "l": "/go/p/c4ec4896c/2ace29e87/d4f678b43", "m": "evomag.ro", "p": 366.99}, {"t": "Hub Usb Satechi PRO hub slim pentru Macbook, 2 x USB A/ C, 4K HDMI, SD/Micro SD, (Argintiu)", "i": "https://static2.evomag.ro/img?extend=white&file=products%2F4098%2F4098770%2F64802ddf6cc74.png&type=auto&width=500&sign=CmHPIXOCEgbJHzRqVp7EifEWwcXvTj91zJHk6m2lyIM", "l": "/go/p/2e01baf79/2ace29e87/d4f678b43", "m": "evomag.ro", "p": 335.99}, {"t": "Tastatura Wireless Satechi X2 Slim Bluetooth retroiluminata cu Keypad numeric, US (Gri)", "i": "https://static2.evomag.ro/img?extend=white&file=products%2F4098%2F4098693%2F64802dfb0d56e.jpg&type=auto&width=500&sign=z64vBxcpYxdLyXn5rC1zlv8MBKnGP8NaCoHyk5-NRZA", "l": "/go/p/7bfb40734/2ace29e87/d4f678b43", "m": "evomag.ro", "p": 322.99}, {"t": "Hub multiport USB, Satechi, Compatibil cu Apple, HDMI 4K, Gri", "i": "https://static2.evomag.ro/img?extend=white&file=products%2F3935%2F3935739%2F628e2fa437a80.jpg&type=auto&width=500&sign=asBsoYd4_qZO_3xGlfLrY_Am87w0mRBVLiWFaCMuFmU", "l": "/go/p/a4a07ba0d/2ace29e87/d4f678b43", "m": "evomag.ro", "p": 314.99}, {"t": "Hub Usb Satechi PRO hub slim pentru Macbook, 2 x USB A/ C, 4K HDMI, SD/Micro SD (Gri)", "i": "https://static2.evomag.ro/img?extend=white&file=products%2F4098%2F4098771%2F64802de71cadd.png&type=auto&width=500&sign=aCvGeKU19IqoLOkwSBsdhH17dghDhlOv4-mfuoDSI-Y", "l": "/go/p/e40014eb5/2ace29e87/d4f678b43", "m": "evomag.ro", "p": 304.99}, {"t": "Hub Usb Satechi PRO hub slim pentru Macbook, 2 x USB A / Type C, 4K HDMI, SD/Micro SD (Negru)", "i": "https://static2.evomag.ro/img?extend=white&file=products%2F4098%2F4098768%2F64802df05d42c.png&type=auto&width=500&sign=Az7VWF_emU2Cu1rMvI9rYUM9xdmbMCtgH43txTjWcv0", "l": "/go/p/4ced147ca/2ace29e87/d4f678b43", "m": "evomag.ro", "p": 304.99}, {"t": "Adaptor Multimedia Satechi Slim ST-CMAG, Type-C (Auriu)", "i": "https://static2.evomag.ro/img?extend=white&file=products%2F3790%2F3790408%2F1591095214Adaptor+Multimedia+Satechi+Slim+ST-CMAG%2C+Type-C+%28Auriu%291.jpg&type=auto&width=500&sign=HngMYSArtOR5lr_KNeU9g6bYeAVZyzBQcJMZHDE1rPo", "l": "/go/p/uYwlq9nhcO6W/2ace29e87/d4f678b43", "m": "evomag.ro", "p": 301.99}, {"t": "Docking Station Satechi Slim ST-CMAM, Type-C (Gri)", "i": "https://static2.evomag.ro/img?extend=white&file=products%2F3790%2F3790409%2F1591094530Adaptor+Multimedia+Satechi+Slim+ST-CMAS%2C+Type-C+%28Gri%291.jpg&type=auto&width=500&sign=Mgk8-0kopK8QEtWbJNWhc_BhvZForsUB_NWTjDB3gZs", "l": "/go/p/ikvrRPs_1YuE/2ace29e87/d4f678b43", "m": "evomag.ro", "p": 301.99}, {"t": "HUB USB Satechi 4-in-1 ST-H3C25EM, USB-C, 2.5 Gigabit Ethernet (Gri)", "i": "https://static2.evomag.ro/img?extend=white&file=products%2F4205%2F4205718%2Fsatechi-4-in-1-usb-c-hub-with-67b5adb7b7bbd.jpg&type=auto&width=500&sign=NlG9hVBkccdvEFNexArQHS_RWpV39_P9ZUVjTKXSofo", "l": "/go/p/ea0bf76f5/2ace29e87/d4f678b43", "m": "evomag.ro", "p": 292.99}, {"t": "Portofel din piele vegana Satechi ST-VPCK, Husa de pasaport, Find My Tracker (Negru)", "i": "https://static2.evomag.ro/img?extend=white&file=products%2F4205%2F4205747%2Fsatechi-vegan-leather-passport-67b5c3abf40ce.jpg&type=auto&width=500&sign=guAcpfHCeBW5copIK-1z3U6gTEuqSPqXJs-wLo49gr0", "l": "/go/p/5a854d433/2ace29e87/d4f678b43", "m": "evomag.ro", "p": 292.99}, {"t": "Suport auto cu incarcare wireless Satechi ST-Q2CCM, Qi 2, 10 W (Gri)", "i": "https://static2.evomag.ro/img?extend=white&file=products%2F4205%2F4205689%2Fsatechi-qi2-wireless-car-charg-67b59fab9ae5e.jpg&type=auto&width=500&sign=rrGHs97kpAg71UmiKfWAa9oMYf2WDBqBoPSMRrI13lU", "l": "/go/p/75444c637/2ace29e87/d4f678b43", "m": "evomag.ro", "p": 292.99}, {"t": "Docking station Satechi Aluminium TYPE-C PRO Hub, Ethernet, Silver", "i": "https://static2.evomag.ro/img?extend=white&file=products%2F3848%2F3848615%2F62174acd1926a.jpg&type=auto&width=500&sign=ZUzP5vQMi_7Gb3FsLjVQCcEHZcS0iB3OFszBomtxJ_U", "l": "/go/p/a85185939/2ace29e87/d4f678b43", "m": "evomag.ro", "p": 284.99}, {"t": "Hub hibrid USB-C Satechi din aluminiu, compartiment SSD, HDMI 4K, 2 x USB-A 3.1 Gen 2 pâna la 10 Gbps, Negru", "i": "https://static2.evomag.ro/img?extend=white&file=products%2F4098%2F4098895%2F64802dfac5d13.jpg&type=auto&width=500&sign=5knAfSstPiMbngAg4W22sgNMcmPpMRIyoQmUyCkR4p8", "l": "/go/p/e6a5cdc03/2ace29e87/d4f678b43", "m": "evomag.ro", "p": 280.99}, {"t": "Incarcator Satechi pentru Apple Watch si AirPods USB-C, 2.5 W (Alb)", "i": "https://static2.evomag.ro/img?extend=white&file=products%2F4223%2F4223008%2F682c44ecd0b2d.jpg&type=auto&width=500&sign=C7HPCBbFgOysaIOEJjycAjOJJbYwxTIcum3C2CBfiK4", "l": "/go/p/oxG9QEjpCyIU/2ace29e87/d4f678b43", "m": "evomag.ro", "p": 279.99}, {"t": "Carcasa Satechi Mini NVMe SSD Enclosure 2230 mm, 10 Gbps, USB-C, Pentru iPhone/Macbook/PC (Gri)", "i": "https://static2.evomag.ro/img?extend=white&file=products%2F4285%2F4285259%2F69a597d964ef2.jpg&type=auto&width=500&sign=OsyzNBIKUJCx05RCnmq7wH0zc2EMkD-Ne5SWA82YFcI", "l": "/go/p/VUqiTGcQK_C4/2ace29e87/d4f678b43", "m": "evomag.ro", "p": 264.99}, {"t": "Adaptor Satechi USB Type-C - HDMI, 4K 60HZ, 1.8m (Argintiu)", "i": "https://static2.evomag.ro/img?extend=white&file=products%2F3790%2F3790400%2F1591093182Adaptor+Satechi+USB+Type-C+-+HDMI%2C+4K+60HZ%2C+1.8m+%28Argintiu%291.jpg&type=auto&width=500&sign=9Ka_XK-ysagixPYObwmSUqRSLa9cvga8gv5C_FTAHOM", "l": "/go/p/QaX48zkJtRHV/2ace29e87/d4f678b43", "m": "evomag.ro", "p": 221.99}, {"t": "Cablu de incarcare magnetic Satechi ST-QCAWM pentru Apple Watch Seria 1-10, Watch Ultra si Ultra 2, Fast-Charge (Gri)", "i": "https://static2.evomag.ro/img?extend=white&file=products%2F4205%2F4205733%2Fsatechi-usb-c-magnetic-fast-ch-67b5bc9766c0d.png&type=auto&width=500&sign=wNxCymxfWKe8TIUujQwXj5XuzYVNQIA4J1351yj3A64", "l": "/go/p/cf9dc659a/2ace29e87/d4f678b43", "m": "evomag.ro", "p": 221.99}, {"t": "Carcasa laptop Macbook Pro 16inch Satechi ECO-Hardshell, Matte Clear", "i": "https://static2.evomag.ro/img?extend=white&file=products%2F4200%2F4200476%2F67909282c1467.jpg&type=auto&width=500&sign=P5Cxy3uJ3QZeiyrmqA4Nf9KXdbEjhMieJBtodt4O8gg", "l": "/go/p/7bc1e942b/2ace29e87/d4f678b43", "m": "evomag.ro", "p": 215.99}, {"t": "Carcasa laptop Macbook Pro 16inch Satechi ECO-Hardshell, Matte (Negru)", "i": "https://static2.evomag.ro/img?extend=white&file=products%2F4200%2F4200477%2F6790928d1cc46.jpg&type=auto&width=500&sign=6kVuqAtZdsUep55HmFlX2X75oY3qvpVjEF5DSu8kO8o", "l": "/go/p/9ec77f8f1/2ace29e87/d4f678b43", "m": "evomag.ro", "p": 215.99}, {"t": "Telecomanda de prezentare, SATECHI, R1, Bluetooth (Gri)", "i": "https://static2.evomag.ro/img?extend=white&file=products%2F4199%2F4199759%2F6790922f2c539.png&type=auto&width=500&sign=EDdIqM4ipf49LasVpknGHDusvlh5Ke-T_vH0jYPVJS8", "l": "/go/p/87dd28b17/2ace29e87/d4f678b43", "m": "evomag.ro", "p": 215.99}, {"t": "Card pocket, Satechi, Vegan-Piele Magnetic, Portocaliu", "i": "https://static2.evomag.ro/img?extend=white&file=products%2F4133%2F4133971%2F6582c2f08f7e9.png&type=auto&width=500&sign=wEWx95M--dE6niIRshVWKTQmBcPosHPWFNRA13GIP2o", "l": "/go/p/6e8185f4f/2ace29e87/d4f678b43", "m": "evomag.ro", "p": 215.99}, {"t": "Card pocket Satechi ST-VLWB, Vegan-Piele Magnetic, Alabastru", "i": "https://static2.evomag.ro/img?extend=white&file=products%2F4133%2F4133968%2F6582c2ea5159e.png&type=auto&width=500&sign=pS1euBsEMTVvxxXi_DgJvHxpvup34FrDOJqycaCotS4", "l": "/go/p/8d95a32bb/2ace29e87/d4f678b43", "m": "evomag.ro", "p": 215.99}, {"t": "Card pocket, Satechi, Vegan-Piele Magnetic, Maro", "i": "https://static2.evomag.ro/img?extend=white&file=products%2F4133%2F4133970%2F6582c2f067369.png&type=auto&width=500&sign=ZpZgpzunVKctMfx3R12pIe-8IzTGYp6YQ9ey7mqt0Xw", "l": "/go/p/8ff3bb73c/2ace29e87/d4f678b43", "m": "evomag.ro", "p": 215.99}, {"t": "Mouse Pad Satechi Vegan-Leather Premium Desk Mat ST-LPDMN, 680 x 314 (Maro)", "i": "https://static2.evomag.ro/img?extend=white&file=products%2F4205%2F4205304%2Fsatechi-vegan-leather-premium-67b31c63504e2.jpg&type=auto&width=500&sign=tdD8CNLLOneULa7_HkFutMW6PiGQrhGRapDxjLak1h8", "l": "/go/p/a3238b40f/2ace29e87/d4f678b43", "m": "evomag.ro", "p": 200.99}, {"t": "Stand ajustabil Satechi R1 din aluminiu pentru tableta sau laptop (Gri)", "i": "https://static2.evomag.ro/img?extend=white&file=products%2F4098%2F4098486%2F64802db6836ee.jpg&type=auto&width=500&sign=UaxVWofZGDSUxp31J78OWmdE8AgVJ5lI935XNZbHWmo", "l": "/go/p/35d5bae09/2ace29e87/d4f678b43", "m": "evomag.ro", "p": 200.99}, {"t": "Suport dual vertical Satechi pentru laptop, tablete si telefoane (Argintiu)", "i": "https://static2.evomag.ro/img?extend=white&file=products%2F4098%2F4098487%2F64802dc827de9.jpg&type=auto&width=500&sign=yY7Gayoqa8byUYph2V4e3KhhH3Sm1obgXXi6kvaw-l0", "l": "/go/p/e7076efe7/2ace29e87/d4f678b43", "m": "evomag.ro", "p": 200.99}, {"t": "Incarcator Wireless Satechi Magnetic, pentru Apple Watch, 5W (Negru)", "i": "https://static2.evomag.ro/img?extend=white&file=products%2F3849%2F3849355%2F62174acbedaa1.jpg&type=auto&width=500&sign=enQVgAUesmlVuP-gju5q77izimZaEU01JxyxhsoQwIM", "l": "/go/p/422b9c27c/2ace29e87/d4f678b43", "m": "evomag.ro", "p": 200.99}, {"t": "Mouse Pad Satechi Vegan-Leather Premium Desk Mat ST-LPDMB, 680 x 314 (Albastru)", "i": "https://static2.evomag.ro/img?extend=white&file=products%2F4205%2F4205303%2Fsatechi-vegan-leather-premium-67b31d3f4c7ba.jpg&type=auto&width=500&sign=udJ-BxOblhPmDzzeEi8VW35-VW7qBhPSLhR-KxM907Y", "l": "/go/p/c443c9ab5/2ace29e87/d4f678b43", "m": "evomag.ro", "p": 163.99}, {"t": "Adaptor Satechi Type-C - VGA, 60Hz (Gri)", "i": "https://static2.evomag.ro/img?extend=white&file=products%2F3777%2F3777364%2F1576070060Adaptor+Satechi+Type-C+-+VGA%2C+60Hz+%28Gri%291.JPG&type=auto&width=500&sign=xNM5N80pYyBd1xQvUblZUkoJid1_9hpYrf2_24KXk18", "l": "/go/p/7dd3249bd/2ace29e87/d4f678b43", "m": "evomag.ro", "p": 159.99}, {"t": "Adaptor Satechi USB Type-C - HDMI, 4K 60HZ (Gri)", "i": "https://static2.evomag.ro/img?extend=white&file=products%2F3776%2F3776773%2F1575646191Adaptor+Satechi+USB+Type-C+-+HDMI%2C+4K+60HZ+%28Gri%291.JPG&type=auto&width=500&sign=_iKmS9KLlM3AROfyPlp0zHyc8HJUHtAzylbGSJARy3A", "l": "/go/p/b3b84fc1f/2ace29e87/d4f678b43", "m": "evomag.ro", "p": 155.99}, {"t": "Adaptor Satechi Type-C - RJ45, Gigabit (Gri)", "i": "https://static2.evomag.ro/img?extend=white&file=products%2F3776%2F3776574%2F1575472916Adaptor+Satechi+Type-C+-+RJ45%2C+Gigabit+%28Gri%291.JPG&type=auto&width=500&sign=M1812OMiDqS2GOIP-P0noWHZ1JUhcPbjtuUjQ-JV4Zs", "l": "/go/p/e7ade6979/2ace29e87/d4f678b43", "m": "evomag.ro", "p": 150.99}, {"t": "Adaptor Satechi Type-C - VGA, 60Hz (Argintiu)", "i": "https://static2.evomag.ro/img?extend=white&file=products%2F3777%2F3777366%2F1576071472Adaptor+Satechi+Type-C+-+VGA%2C+60Hz+%28Argintiu%291.JPG&type=auto&width=500&sign=EggIUxbXjSWVOQKLb87tLxlFLSr57PyME2bIh9Q1O-o", "l": "/go/p/aa45c118b/2ace29e87/d4f678b43", "m": "evomag.ro", "p": 127.99}, {"t": "Adaptor Satechi ST-UCATCM, USB Type-C - USB 3.0 (Gri)", "i": "https://static2.evomag.ro/img?extend=white&file=products%2F4028%2F4028642%2Fadaptor-satechi-st-ucatcm-usb-6360eda99a5a9.JPG&type=auto&width=500&sign=GYCP_PaVgpMtlqOrQ19hThPZ7tiRhjCGzMIfDTYAHGM", "l": "/go/p/51881ad56/2ace29e87/d4f678b43", "m": "evomag.ro", "p": 97.99}, {"t": "Adaptor Satechi ST-TCUAM, USB - USB Type-C (Gri)", "i": "https://static2.evomag.ro/img?extend=white&file=products%2F3782%2F3782273%2F1582025269Adaptor+Satechi+ST-TCUAM%2C+USB+-+USB+Type-C+%28Gri%291.JPG&type=auto&width=500&sign=c6nwTCugFyFr7OkGv8ZPEXhFHzodfzpfUBesVz2ErJs", "l": "/go/p/0e2862925/2ace29e87/d4f678b43", "m": "evomag.ro", "p": 73.99}, {"t": "Adaptor Satechi ST-TAUCM, USB Type-C - USB (Gri)", "i": "https://static2.evomag.ro/img?extend=white&file=products%2F3778%2F3778822%2F1576856966Adaptor+Satechi+ST-TAUCM%2C+USB+Type-C+-+USB+1.jpg&type=auto&width=500&sign=Sg7WxewZP29iIBTRIEZ80_VUMh53BjvJQjVxKzt0w74", "l": "/go/p/9868c8c08/2ace29e87/d4f678b43", "m": "evomag.ro", "p": 48.99}, {"t": "Adaptor Satechi ST-TAUCS, USB Type-C - USB (Argintiu)", "i": "https://static2.evomag.ro/img?extend=white&file=products%2F3778%2F3778823%2F1576855613Adaptor+Satechi+ST-TAUCM%2C+USB+Type-C+-+USB+%28Gri%291.jpg&type=auto&width=500&sign=5R3uwvg9qNcCzMCfILDyKFNEWpSXh03q5iu9LuNiUUM", "l": "/go/p/850e37d42/2ace29e87/d4f678b43", "m": "evomag.ro", "p": 48.99}]